harlequin_cassandra/__init__.py
harlequin_cassandra/adapter.py
harlequin_cassandra/cli_options.py
harlequin_cassandra/completions.py
harlequin_cassandra/keywords.tsv
harlequin_cassandra/py.typed
harlequin_cassandra-0.1.3.dist-info/LICENSE
harlequin_cassandra-0.1.3.dist-info/METADATA
harlequin_cassandra-0.1.3.dist-info/WHEEL
harlequin_cassandra-0.1.3.dist-info/entry_points.txt
harlequin_cassandra-0.1.3.dist-info/RECORD
