Metadata-Version: 2.3
Name: harlequin-cassandra
Version: 0.1.3
Summary: A Harlequin adapter for Cassandra.
License: MIT
Author: Vadim Khitrin
Author-email: me@vkhitrin.com
Requires-Python: >=3.9,<3.13
Classifier: License :: OSI Approved :: MIT License
Classifier: Programming Language :: Python :: 3
Classifier: Programming Language :: Python :: 3.9
Classifier: Programming Language :: Python :: 3.10
Classifier: Programming Language :: Python :: 3.11
Classifier: Programming Language :: Python :: 3.12
Requires-Dist: cassandra-driver (>=3.29.1,<4.0.0)
Requires-Dist: harlequin (>=1.25,<3)
Project-URL: Repository, https://github.com/vkhitrin/harlequin-cassandra
